vk_parser/__init__.py
vk_parser/collector.py
vk_parser/config.ini.example
vk_parser/main.py
vk_parser/api/__init__.py
vk_parser/api/vk_client.py
vk_parser/config/__init__.py
vk_parser/config/settings.py
vk_parser/models/__init__.py
vk_parser/models/user.py
vk_parser/utils/__init__.py
vk_parser/utils/clean_logs.py
vk_parser/utils/logging_setup.py
vk_parser/utils/state_manager.py
vk_parser/utils/storage.py
vk_parser-0.2.0.dist-info/licenses/LICENSE
vk_parser-0.2.0.dist-info/METADATA
vk_parser-0.2.0.dist-info/WHEEL
vk_parser-0.2.0.dist-info/entry_points.txt
vk_parser-0.2.0.dist-info/top_level.txt
vk_parser-0.2.0.dist-info/RECORD
