Metadata-Version: 2.4
Name: vk-parser
Version: 0.2.0
Summary: Модульный парсер данных пользователей из социальной сети ВКонтакте
Home-page: https://github.com/johnneon/vk-parser
Author: Efimovich Evgenii
Author-email: neon.1598@mail.ru
Classifier: Programming Language :: Python :: 3
Classifier: Programming Language :: Python :: 3.7
Classifier: Programming Language :: Python :: 3.8
Classifier: Programming Language :: Python :: 3.9
Classifier: Programming Language :: Python :: 3.10
Classifier: License :: OSI Approved :: MIT License
Classifier: Operating System :: OS Independent
Classifier: Development Status :: 4 - Beta
Classifier: Intended Audience :: Developers
Classifier: Intended Audience :: Science/Research
Classifier: Topic :: Scientific/Engineering :: Information Analysis
Requires-Python: >=3.7
License-File: LICENSE
Requires-Dist: vk_api>=11.9.9
Requires-Dist: asyncio>=3.4.3
Requires-Dist: aiohttp>=3.8.3
Requires-Dist: tqdm>=4.62.3
Dynamic: author
Dynamic: author-email
Dynamic: classifier
Dynamic: description
Dynamic: description-content-type
Dynamic: home-page
Dynamic: license-file
Dynamic: requires-dist
Dynamic: requires-python
Dynamic: summary
